formate_trailing_commas/_vendor/add_trailing_comma/_plugins/__init__.py
formate_trailing_commas/_vendor/add_trailing_comma/_plugins/_with.py
formate_trailing_commas/_vendor/add_trailing_comma/_plugins/calls.py
formate_trailing_commas/_vendor/add_trailing_comma/_plugins/classes.py
formate_trailing_commas/_vendor/add_trailing_comma/_plugins/functions.py
formate_trailing_commas/_vendor/add_trailing_comma/_plugins/imports.py
formate_trailing_commas/_vendor/add_trailing_comma/_plugins/literals.py
formate_trailing_commas/_vendor/add_trailing_comma/_plugins/match.py
formate_trailing_commas/_vendor/add_trailing_comma/LICENSE
formate_trailing_commas/_vendor/add_trailing_comma/__init__.py
formate_trailing_commas/_vendor/add_trailing_comma/__main__.py
formate_trailing_commas/_vendor/add_trailing_comma/_ast_helpers.py
formate_trailing_commas/_vendor/add_trailing_comma/_data.py
formate_trailing_commas/_vendor/add_trailing_comma/_main.py
formate_trailing_commas/_vendor/add_trailing_comma/_token_helpers.py
formate_trailing_commas/_vendor/add_trailing_comma.pyi
formate_trailing_commas/_vendor/requirements.txt
formate_trailing_commas/__init__.py
formate_trailing_commas/py.typed
formate_trailing_commas-0.1.1.dist-info/LICENSE
formate_trailing_commas-0.1.1.dist-info/METADATA
formate_trailing_commas-0.1.1.dist-info/WHEEL
formate_trailing_commas-0.1.1.dist-info/entry_points.txt
formate_trailing_commas-0.1.1.dist-info/RECORD
