Metadata-Version: 2.2
Name: formate-trailing-commas
Version: 0.1.1
Summary: Formate plugin to add trailing commas.
Author-email: Dominic Davis-Foster <dominic@davis-foster.co.uk>
License: MIT
Keywords: commas,formate,formatting,linting
Home-page: https://github.com/python-formate/formate-trailing-commas
Project-URL: Issue Tracker, https://github.com/python-formate/formate-trailing-commas/issues
Project-URL: Source Code, https://github.com/python-formate/formate-trailing-commas
Platform: Windows
Platform: macOS
Platform: Linux
Classifier: Development Status :: 4 - Beta
Classifier: Environment :: Console
Classifier: Intended Audience :: Developers
Classifier: License :: OSI Approved :: MIT License
Classifier: Operating System :: OS Independent
Classifier: Programming Language :: Python
Classifier: Programming Language :: Python :: 3 :: Only
Classifier: Programming Language :: Python :: 3.7
Classifier: Programming Language :: Python :: 3.8
Classifier: Programming Language :: Python :: 3.9
Classifier: Programming Language :: Python :: 3.10
Classifier: Programming Language :: Python :: 3.11
Classifier: Programming Language :: Python :: 3.12
Classifier: Programming Language :: Python :: 3.13
Classifier: Programming Language :: Python :: Implementation :: CPython
Classifier: Typing :: Typed
Requires-Python: >=3.7
Requires-Dist: formate>=0.4.4
Requires-Dist: tokenize-rt>=3.0.1
